README.md
setup.py
Tanker.egg-info/PKG-INFO
Tanker.egg-info/SOURCES.txt
Tanker.egg-info/dependency_links.txt
Tanker.egg-info/entry_points.txt
Tanker.egg-info/top_level.txt
tanker/__init__.py
tanker/cli.py
tanker/context.py
tanker/expression.py
tanker/table.py
tanker/utils.py
tanker/view.py