Metadata-Version: 1.0
Name: Tanker
Version: 0.8.7
Summary: Tanker is a Python database library targeting analytic operations
Home-page: https://github.com/bertrandchenal/tanker
Author: Bertrand Chenal
Author-email: bertrand@adimian.com
License: MIT
Platform: UNKNOWN
